libsimba/__init__.py
libsimba/auth/__init__.py
libsimba/auth/client_credentials.py
libsimba/config.py
libsimba/exceptions.py
libsimba/logging.conf
libsimba/param_checking.py
libsimba/schemas.py
libsimba/simba.py
libsimba/simba_contract.py
libsimba/simba_contract_sync.py
libsimba/simba_request.py
libsimba/simba_sync.py
libsimba/utils.py
libsimba/wallet.py
libsimba-1.7.7.dist-info/LICENSE
libsimba-1.7.7.dist-info/METADATA
libsimba-1.7.7.dist-info/WHEEL
libsimba-1.7.7.dist-info/RECORD
