Metadata-Version: 2.3
Name: libsimba
Version: 1.7.7
Summary: libsimba is a library simplifying the use of SIMBAChain Blocks APIs.
License: MIT
Author: SIMBA Chain Inc.
Requires-Python: >=3.9,<4.0
Classifier: License :: OSI Approved :: MIT License
Classifier: Programming Language :: Python :: 3
Classifier: Programming Language :: Python :: 3.9
Classifier: Programming Language :: Python :: 3.10
Classifier: Programming Language :: Python :: 3.11
Classifier: Programming Language :: Python :: 3.12
Classifier: Programming Language :: Python :: 3.13
Requires-Dist: httpx (>=0.26.0)
Requires-Dist: pydantic (>=2.1.1,<=3)
Requires-Dist: pydantic-settings (>=2.1.0,<3)
Project-URL: Documentation, https://simbachain.github.io/libsimba/
Project-URL: Homepage, https://github.com/SIMBAChain/libsimba
Project-URL: Repository, https://github.com/SIMBAChain/libsimba
